{
  "hero": {
    "title": "نصنع المستقبل",
    "subtitle": "انضم إلينا في قيادة التغيير من خلال الاستشارات الاستراتيجية",
    "button": "استكشف خدماتنا"
  },
  "accelerate": {
    "title": "نسرّع المستقبل",
    "subtitle": "متخصصون في زيادة سرعة التحول في مختلف القطاعات"
  },
  "beyondBorders": {
    "title": "ما وراء الحدود",
    "subtitle": "احصل على قوة الشراكات الاقتصادية العابرة للحدود"
  },
  "futureNow": {
    "title": "المستقبل الآن",
    "quote": "تتخيل المستقبل؟ انضم إلينا في قيادة التميز الاقتصادي من خلال الرؤى الخبيرة",
    "description": "نقود النمو الأمثل، من خلال استراتيجيات قائمة على البيانات وحلول اقتصادية مخصصة، مما يحفز الأداء المستدام."
  },
  "scaleFuture": {
    "title": "توسيع نطاق المستقبل",
    "description": "نركز على تحديد الفرص الاقتصادية، ونقدر الاستشارات القائمة على الأدلة لإنشاء قيمة طويلة المدى"
  },
  "chairman": {
    "title": "خالد عقله الدقماق",
    "position": "رئيس مجلس الإدارة",
    "message": "نفخر بحضورنا الراسخ في الجمهورية العربية السورية والمملكة العربية السعودية، حيث نقدم حلولاً اقتصادية واستثمارية مخصصة تهدف إلى تعزيز النمو وتحقيق النجاح على المدى الطويل. من خلال دمج الخبرات المحلية والرؤى العالمية، نلتزم بمساعدة عملائنا على التنقل بفعالية في كلا السوقين، مما يضمن تحقيق تأثير مستدام وخلق قيمة حقيقية."
  },
  "partner": {
    "title": "حسن بالولي",
    "position": "الشريك المدير",
    "message": "في همة، نعمل على استثمار القوة الكامنة للاستثمارات الاستراتيجية لدعم النمو و الابتكار في القطاعات الاقتصادية الحيوية. بفضل خبرتنا العميقة و شبكة علاقاتنا الواسعة في كل من الجمهورية العربية السورية والمملكة العربية السعودية، نتمتع بمكانة استراتيجية تمكننا من مساعدة عملائنا في التكيف مع التغيرات الديناميكية و النمو المتسارع في هذه الأسواق. تتيح لنا علاقاتنا العالمية مع أبرز الشركات في قطاعات الطاقة، والبنية التحتية، والإنشاءات، والاتصالات تقديم حلول تجمع بين التخصص المحلي والتأثير العالمي، مما يحقق قيمة حقيقية لعملائنا. من خلال دمج رؤانا المحلية مع الخبرات الدولية، نحدد الفرص المميزة ونفتح آفاقًا جديدة تساهم في تحقيق النجاح المستدام على المدى الطويل. نحن ملتزمون ببناء علاقات شراكة دائمة، وخلق تأثير إيجابي مستدام، وإرشاد عملائنا نحو مستقبل واعد."
  },
  "services": {
    "title": "خدماتنا",
    "subtitle": "نقدم مجموعة شاملة من الخدمات الاستشارية الاقتصادية والاستثمارية",
    "services": [
      {
        "title": "الاستشارات الاقتصادية",
        "description": "تحليل شامل للأوضاع الاقتصادية وتقديم التوصيات الاستراتيجية لتحقيق النمو المستدام",
        "icon": "BarChart3"
      },
      {
        "title": "الاستشارات الاستثمارية",
        "description": "إرشاد المستثمرين لاتخاذ قرارات استثمارية مدروسة وفعالة تحقق أفضل العوائد",
        "icon": "TrendingUp"
      },
      {
        "title": "دراسات السوق والجدوى",
        "description": "تحليل متعمق للأسواق وإعداد دراسات الجدوى الاقتصادية للمشاريع والاستثمارات",
        "icon": "LineChart"
      },
      {
        "title": "استشارات الاستراتيجية المالية",
        "description": "تطوير استراتيجيات مالية شاملة تدعم أهداف النمو والتوسع طويلة المدى",
        "icon": "Target"
      },
      {
        "title": "استشارات تطوير الأعمال",
        "description": "دعم الشركات في تطوير استراتيجيات النمو وتحسين الأداء التشغيلي",
        "icon": "Rocket"
      },
      {
        "title": "تحليل السياسات والأثر الاقتصادي",
        "description": "تقييم أثر السياسات الاقتصادية وتقديم التوصيات لصانعي القرار",
        "icon": "FileText"
      }
    ]
  }
}